pbrm/__init__.py
pbrm/change_repository.py
pbrm/command_process.py
pbrm/config.py
pbrm/delete.py
pbrm/error.py
pbrm/gif.py
pbrm/main.py
pbrm/pbrm_statistics.py
pbrm/save_illust.py
pbrm/update.py
pbrm/user_download.py
pbrm/utils.py
pbrm/zip.py
pbrm/spider/__init__.py
pbrm/spider/cookie_verify.py
pbrm/spider/get_bookmarks.py
pbrm/spider/get_meta.py
pbrm/spider/get_user_illusts.py
pbrm/spider/illust_download.py
pbrm/web_server/__init__.py
pbrm/web_server/illust_page.py
pbrm/web_server/image.py
pbrm/web_server/image_compress.py
pbrm/web_server/main_page.py
pbrm/web_server/template/main_page.tpl
pbrm-0.2.4.dist-info/METADATA
pbrm-0.2.4.dist-info/WHEEL
pbrm-0.2.4.dist-info/entry_points.txt
pbrm-0.2.4.dist-info/top_level.txt
pbrm-0.2.4.dist-info/RECORD
