Metadata-Version: 2.2
Name: pbrm
Version: 0.2.4
Summary: A pixiv bookmarks local backup tool
Home-page: https://github.com/stay-miku/pixivBookmarksRepositoryManager
Author: stay_miku
Author-email: miku@miku.pics
Requires-Dist: requests
Requires-Dist: lxml
Requires-Dist: docopt
Requires-Dist: bottle
Dynamic: author
Dynamic: author-email
Dynamic: home-page
Dynamic: requires-dist
Dynamic: summary
